{"assets/Bees.svg":["assets/Bees.svg"],"assets/JN-logo.png":["assets/JN-logo.png"],"assets/JN-logo.svg":["assets/JN-logo.svg"],"assets/Juan-Nino-CV.pdf":["assets/Juan-Nino-CV.pdf"],"assets/github-jn.svg":["assets/github-jn.svg"],"assets/hex-b.png":["assets/hex-b.png"],"assets/hex-bl.png":["assets/hex-bl.png"],"assets/hex-g.png":["assets/hex-g.png"],"assets/hex-gl.png":["assets/hex-gl.png"],"assets/linkedin-jn.svg":["assets/linkedin-jn.svg"],"assets/profile.png":["assets/profile.png"],"packages/cupertino_icons/assets/CupertinoIcons.ttf":["packages/cupertino_icons/assets/CupertinoIcons.ttf"]}